{
  "compressionlevel": -1,
  "width": 11,
  "height": 9,
  "infinite": false,
  "orientation": "orthogonal",
  "renderorder": "right-down",
  "tilewidth": 16,
  "tileheight": 16,
  "type": "map",
  "version": "1.10",
  "tiledversion": "1.10.0",
  "layers": [
    {
      "id": 1,
      "name": "ground",
      "type": "tilelayer",
      "width": 11,
      "height": 9,
      "x": 0,
      "y": 0,
      "opacity": 1,
      "visible": true,
      "data": [
        217,
        218,
        173,
        174,
        156,
        171,
        156,
        354,
        354,
        369,
        370,
        225,
        226,
        181,
        182,
        164,
        54,
        164,
        362,
        362,
        377,
        378,
        329,
        330,
        285,
        286,
        274,
        283,
        274,
        274,
        274,
        274,
        274,
        274,
        266,
        266,
        292,
        293,
        293,
        293,
        293,
        294,
        266,
        266,
        274,
        266,
        266,
        300,
        295,
        297,
        298,
        296,
        302,
        266,
        266,
        274,
        266,
        266,
        300,
        295,
        305,
        306,
        296,
        302,
        266,
        266,
        343,
        266,
        266,
        308,
        309,
        309,
        309,
        309,
        310,
        266,
        342,
        351,
        266,
        266,
        320,
        328,
        336,
        266,
        266,
        266,
        266,
        350,
        9,
        9,
        9,
        27,
        28,
        29,
        9,
        9,
        9,
        9,
        9
      ]
    },
    {
      "id": 2,
      "name": "collision",
      "type": "tilelayer",
      "width": 11,
      "height": 9,
      "x": 0,
      "y": 0,
      "opacity": 0,
      "visible": false,
      "data": [
        1,
        1,
        1,
        1,
        1,
        1,
        1,
        1,
        1,
        1,
        1,
        1,
        1,
        1,
        1,
        1,
        1,
        1,
        1,
        1,
        1,
        1,
        0,
        0,
        0,
        0,
        0,
        0,
        0,
        0,
        0,
        0,
        0,
        0,
        0,
        0,
        0,
        0,
        0,
        0,
        0,
        0,
        0,
        0,
        0,
        0,
        0,
        0,
        0,
        1,
        1,
        0,
        0,
        0,
        0,
        0,
        0,
        0,
        0,
        0,
        1,
        1,
        0,
        0,
        0,
        0,
        0,
        0,
        0,
        0,
        0,
        0,
        0,
        0,
        0,
        0,
        0,
        1,
        0,
        0,
        0,
        0,
        0,
        0,
        0,
        0,
        0,
        1,
        1,
        1,
        1,
        1,
        1,
        1,
        1,
        1,
        1,
        1,
        1
      ]
    }
  ],
  "tilesets": [
    {
      "firstgid": 1,
      "columns": 16,
      "image": "../tilesets/house1_tileset.png",
      "imagewidth": 256,
      "imageheight": 672,
      "margin": 0,
      "name": "house1_tileset",
      "spacing": 0,
      "tilecount": 664,
      "tilewidth": 16,
      "tileheight": 16
    }
  ]
}